{
  "schemaVersion": 1,
  "userId": "demo-user",
  "user": {
    "userId": "demo-user",
    "nickname": "小明",
    "location": {
      "country": "中国",
      "province": "广东省",
      "city": "深圳市"
    },
    "createdAt": "2026-07-13T00:00:00.000Z",
    "updatedAt": "2026-07-13T00:00:00.000Z"
  },
  "characters": {
    "doubao-sister": {
      "agentId": "doubao-sister",
      "unlocked": true
    },
    "xiaoyu": {
      "agentId": "xiaoyu",
      "unlocked": true
    }
  },
  "stories": {},
  "callCards": {
    "board": {
      "byAgent": {
        "xiaoyu": {
          "pending": [
            {
              "instanceId": "caa1bf9f-bcc2-46ff-b00f-1f2890a2f328",
              "cardId": "xiaoyu_waiting_user",
              "packageId": "golden_handoff",
              "agentId": "xiaoyu",
              "status": "pending",
              "entryMode": "inbound_user_dial",
              "createdAt": "2026-07-14T07:39:21.572Z",
              "updatedAt": "2026-07-14T07:39:21.572Z"
            }
          ]
        }
      }
    }
  },
  "world": {
    "lore": null,
    "facts": [],
    "knowledge": {}
  },
  "schedule": {
    "clockMs": 0,
    "intents": []
  },
  "research": {
    "commitments": []
  },
  "meta": {
    "createdAt": "2026-07-13T00:00:00.000Z",
    "updatedAt": "2026-07-14T07:39:21.576Z",
    "note": "记忆明细在 data/memory/memory.sqlite，不在本文件内嵌"
  },
  "telephony": {
    "redialSlot": {
      "agentId": "xiaoyu",
      "cardId": "xiaoyu_waiting_user"
    }
  }
}
