{
  "schemaVersion": 1,
  "label": "batch-1",
  "at": "2026-07-17T11:42:39.214Z",
  "ok": true,
  "phase": "batch",
  "activeTaskIds": [
    "V2-P1-1",
    "V2-P1-2",
    "V2-P2-1"
  ],
  "reason": "all commands passed",
  "failedCommand": null,
  "exitCode": 0,
  "results": [
    {
      "command": "npm run quality:engine",
      "exitCode": 0,
      "signal": null,
      "error": null,
      "stdout": "[gbx] ▶ verify:npm run quality:engine start cmd=/bin/sh cwd=/Users/bolbiao/workspace/airpc-engine\n\n> quality:engine\n> node scripts/engine-quality/quality-engine.mjs\n\n\n==> check:engine-imports\ncheck:engine-imports ok (51 files)\n\n==> typecheck (@airpc/rpg-engine)\n\n> @airpc/rpg-engine@0.0.1 typecheck\n> tsc -p tsconfig.json --noEmit\n\n\n==> check:engine-structure\nENGINE-STRUCT-002  packages/rpg-engine/src/host/createScheduleClockApi.ts:18:1  当前=95  允许=60  函数 createScheduleClockApi 有效行数 95 超过告警线 60  考虑拆分以保持可测性\nENGINE-STRUCT-003  packages/rpg-engine/src/host/createScheduleClockApi.ts:18:1  当前=11  允许=10  函数 createScheduleClockApi 圈复杂度 11 超过告警线 10  重构条件分支\nENGINE-STRUCT-003  packages/rpg-engine/src/host/wet.ts:140:1  当前=13  允许=10  函数 validateWetAppend 圈复杂度 13 超过告警线 10  重构条件分支\nENGINE-STRUCT-002  packages/rpg-engine/src/host/wet.ts:196:1  当前=62  允许=60  函数 buildWetReplayView 有效行数 62 超过告警线 60  考虑拆分以保持可测性\nENGINE-STRUCT-003  packages/rpg-engine/src/host/wet.ts:196:1  当前=12  允许=10  函数 buildWetReplayView 圈复杂度 12 超过告警线 10  重构条件分支\nENGINE-STRUCT-003  packages/rpg-engine/src/runtime/activeStoryLock.ts:28:1  当前=12  允许=10  函数 asStorySave 圈复杂度 12 超过告警线 10  重构条件分支\nENGINE-STRUCT-003  packages/rpg-engine/src/runtime/activeStoryLock.ts:62:1  当前=11  允许=10  函数 findActiveStoryLock 圈复杂度 11 超过告警线 10  重构条件分支\nENGINE-STRUCT-003  packages/rpg-engine/src/runtime/activeStoryLock.ts:153:1  当前=14  允许=10  函数 activateStoryOnBegin 圈复杂度 14 超过告警线 10  重构条件分支\nENGINE-STRUCT-003  packages/rpg-engine/src/runtime/classifyCall.ts:28:1  当前=14  允许=10  函数 classifyCall 圈复杂度 14 超过告警线 10  重构条件分支\nENGINE-STRUCT-003  packages/rpg-engine/src/runtime/evaluateCondition.ts:7:1  当前=11  允许=10  函数 evaluateExitCondition 圈复杂度 11 超过告警线 10  重构条件分支\nENGINE-STRUCT-002  packages/rpg-engine/src/runtime/exitSelector.ts:20:1  当前=69  允许=60  函数 selectExit 有效行数 69 超过告警线 60  考虑拆分以保持可测性\nENGINE-STRUCT-003  packages/rpg-engine/src/runtime/exitSelector.ts:20:1  当前=12  允许=10  函数 selectExit 圈复杂度 12 超过告警线 10  重构条件分支\nENGINE-STRUCT-002  packages/rpg-engine/src/runtime/freeCallPostPipeline.ts:37:1  当前=88  允许=60  函数 runFreeCallPostPipeline 有效行数 88 超过告警线 60  考虑拆分以保持可测性\nENGINE-STRUCT-003  packages/rpg-engine/src/runtime/freeCallPostPipeline.ts:37:1  当前=11  允许=10  函数 runFreeCallPostPipeline 圈复杂度 11 超过告警线 10  重构条件分支\nENGINE-STRUCT-003  packages/rpg-engine/src/runtime/pickPendingForUserDial.ts:56:1  当前=14  允许=10  函数 pickPendingForIntent 圈复杂度 14 超过告警线 10  重构条件分支\nENGINE-STRUCT-003  packages/rpg-engine/src/schedule/reconcileRecurringIntents.ts:41:1  当前=11  允许=10  函数 reconcileRecurringIntents 圈复杂度 11 超过告警线 10  重构条件分支\nENGINE-STRUCT-003  packages/rpg-engine/src/schedule/writeRecurringIntentFromEffect.ts:47:1  当前=11  允许=10  函数 writeRecurringIntentFromEffect 圈复杂度 11 超过告警线 10  重构条件分支\nENGINE-STRUCT-003  packages/rpg-engine/src/schema/promptScene.ts:63:1  当前=15  允许=10  函数 validatePromptScenePatches 圈复杂度 15 超过告警线 10  重构条件分支\nENGINE-STRUCT-003  packages/rpg-engine/src/tools/resolveToolPolicy.ts:8:1  当前=13  允许=10  函数 resolveToolPolicy 圈复杂度 13 超过告警线 10  重构条件分支\nENGINE-STRUCT-002  packages/rpg-engine/tests/host/a-to-b-memory-e2e.test.ts:17:38  当前=80  允许=60  函数 <anonymous> 有效行数 80 超过告警线 60  考虑拆分以保持可测性\nENGINE-STRUCT-002  packages/rpg-engine/tests/host/a-to-b-memory-e2e.test.ts:27:70  当前=71  允许=60  函数 <anonymous> 有效行数 71 超过告警线 60  考虑拆分以保持可测性\nENGINE-STRUCT-002  packages/rpg-engine/tests/host/chat-turns-e2e.test.ts:17:37  当前=91  允许=60  函数 <anonymous> 有效行数 91 超过告警线 60  考虑拆分以保持可测性\nENGINE-STRUCT-003  packages/rpg-engine/tests/host/chat-turns-e2e.test.ts:17:37  当前=13  允许=10  函数 <anonymous> 圈复杂度 13 超过告警线 10  重构条件分支\nENGINE-STRUCT-002  packages/rpg-engine/tests/host/manual-story-loop.test.ts:21:31  当前=86  允许=60  函数 <anonymous> 有效行数 86 超过告警线 60  考虑拆分以保持可测性\nENGINE-STRUCT-002  packages/rpg-engine/tests/host/night-layer-e2e.test.ts:17:40  当前=75  允许=60  函数 <anonymous> 有效行数 75 超过告警线 60  考虑拆分以保持可测性\nENGINE-STRUCT-002  packages/rpg-engine/tests/host/playback-phase.test.ts:20:40  当前=94  允许=60  函数 <anonymous> 有效行数 94 超过告警线 60  考虑拆分以保持可测性\nENGINE-STRUCT-002  packages/rpg-engine/tests/host/playback-phase.test.ts:30:79  当前=85  允许=60  函数 <anonymous> 有效行数 85 超过告警线 60  考虑拆分以保持可测性\nENGINE-STRUCT-002  packages/rpg-engine/tests/runtime/composer.localHourRange.test.ts:145:56  当前=80  允许=60  函数 <anonymous> 有效行数 80 超过告警线 60  考虑拆分以保持可测性\nENGINE-STRUCT-002  packages/rpg-engine/tests/runtime/pick-pending-entry-mode.test.ts:38:41  当前=86  允许=60  函数 <anonymous> 有效行数 86 超过告警线 60  考虑拆分以保持可测性\nENGINE-STRUCT-002  packages/rpg-engine/tests/schedule/card-reference-and-classify.test.ts:28:43  当前=81  允许=60  函数 <anonymous> 有效行数 81 超过告警线 60  考虑拆分以保持可测性\nENGINE-STRUCT-003  packages/rpg-engine/tests/schedule/card-reference-and-classify.test.ts:28:43  当前=14  允许=10  函数 <anonymous> 圈复杂度 14 超过告警线 10  重构条件分支\nENGINE-STRUCT-009  packages/rpg-engine/src/host:1:1  当前=8  允许=clustered-dirs  目录含 8 个源文件且职责组≥2（card,host,schedule,enginelogfile,errors,types,wet），应分子目录  按职责拆分子目录，禁止长前缀代目录；新增文件勿继续恶化平铺\nENGINE-STRUCT-009  packages/rpg-engine/src/runtime:1:1  当前=12  允许=clustered-dirs  目录含 12 个源文件且职责组≥2（activestorylock,card,composescene,composer,effect,evaluatecondition,exitselector,pickpendingforuserdial,schedule），应分子目录  按职责拆分子目录，禁止长前缀代目录；新增文件勿继续恶化平铺\nENGINE-STRUCT-009  packages/rpg-engine/src/schema:1:1  当前=10  允许=clustered-dirs  目录含 10 个源文件且职责组≥2（asset,card,character,host,outcome,persist,promptscene,schedule,worldfact,worldlore），应分子目录  按职责拆分子目录，禁止长前缀代目录；新增文件勿继续恶化平铺\nENGINE-STRUCT-009  packages/rpg-engine/src/tools:1:1  当前=5  允许=clustered-dirs  目录含 5 个源文件且职责组≥2（builtinregistry,effect,host,resolvetoolpolicy,types），应分子目录  按职责拆分子目录，禁止长前缀代目录；新增文件勿继续恶化平铺\ncheck:engine-structure checked=89 errors=0 warnings=35\n\n==> vitest (@airpc/rpg-engine)\n\n> @airpc/rpg-engine@0.0.1 test\n> vitest run\n\n\n RUN  v3.2.7 /Users/bolbiao/workspace/airpc-engine/packages/rpg-engine\n\n ✓ tests/host/free-call-pipeline.test.ts (4 tests) 184ms\n ✓ tests/host/schedule-once-early-dial.test.ts (3 tests) 184ms\n ✓ tests/host/golden-handoff.test.ts (2 tests) 196ms\n ✓ tests/host/schedule-card-recurring.test.ts (4 tests) 209ms\n ✓ tests/host/engine-plan-7.4-7.5.test.ts (8 tests) 363ms\n ✓ tests/host/engine-plan-7.1-7.3.test.ts (6 tests) 397ms\n ✓ tests/host/schedule-outbound.test.ts (2 tests) 148ms\n ✓ tests/validation/golden-handoff.validate.test.ts (10 tests) 632ms\n ✓ tests/host/night-layer-e2e.test.ts (2 tests) 181ms\n ✓ tests/host/active-story-lock.test.ts (3 tests) 249ms\n ✓ tests/host/refer-to-expert-e2e.test.ts (1 test) 145ms\n ✓ tests/host/clock-tick-e2e.test.ts (4 tests) 473ms\n ✓ tests/host/isolation-recurring-e2e.test.ts (3 tests) 296ms\n ✓ tests/validation/validatePackage.timeBuckets.test.ts (1 test) 72ms\n ✓ tests/host/schedule-no-story-save.test.ts (1 test) 144ms\n ✓ tests/host/content-reload-preserves-session.test.ts (2 tests) 401ms\n   ✓ content reload preserves runtime > loadWorkspace({ resetRuntime: true }) 清空活跃 Session  316ms\n ✓ tests/host/playback-phase.test.ts (1 test) 98ms\n ✓ tests/host/manual-story-loop.test.ts (2 tests) 279ms\n ✓ tests/host/end-story-free-e2e.test.ts (1 test) 106ms\n ✓ tests/host/a-to-b-memory-e2e.test.ts (1 test) 120ms\n ✓ tests/host/chat-turns-e2e.test.ts (2 tests) 250ms\n ✓ tests/host/end-story-next-e2e.test.ts (1 test) 208ms\n ✓ tests/lore/bootstrap-fallback.test.ts (6 tests) 35ms\n ✓ tests/host/wet.test.ts (8 tests) 16ms\n ✓ tests/memory/sqlite-memory.test.ts (8 tests) 59ms\n ✓ tests/runtime/effect-sink-plan-status.test.ts (7 tests) 50ms\n ✓ tests/schedule/card-reference-and-classify.test.ts (9 tests) 5ms\n ✓ tests/runtime/effect-s11.test.ts (5 tests) 5ms\n ✓ tests/runtime/pick-pending-entry-mode.test.ts (4 tests) 3ms\n ✓ tests/runtime/end-story-cleanup.test.ts (5 tests) 6ms\n ✓ tests/runtime/select-call-flow-prompt.test.ts (2 tests) 2ms\n ✓ tests/runtime/composer.test.ts (6 tests) 5ms\n ✓ tests/runtime/composer.localHourRange.test.ts (7 tests) 6ms\n ✓ tests/schema/callcard-schema-tighten.test.ts (4 tests) 3ms\n ✓ tests/schema/user-schema.test.ts (4 tests) 3ms\n ✓ tests/host/log-redact.test.ts (1 test) 1ms\n ✓ tests/runtime/exit-selector.test.ts (3 tests) 1ms\n ✓ tests/index.smoke.test.ts (1 test) 1ms\n\n Test Files  38 passed (38)\n      Tests  144 passed (144)\n   Start at  19:42:29\n   Duration  3.04s (transform 941ms, setup 0ms, collect 8.22s, tests 5.53s, environment 5ms, prepare 1.88s)\n\n\n==> gate self-tests (engine-structure)\n▶ check:engine-structure\n  ✔ 有效行数忽略空行 (0.45275ms)\n  ✔ host 文件分类 (0.121583ms)\n  ✔ 圈复杂度统计分支 (3.227625ms)\n  ✔ 新文件超过文件硬上限失败 (12.705042ms)\n  ✔ 新函数超过函数硬上限失败 (2.754583ms)\n  ✔ 圈复杂度超过硬上限失败 (1.431458ms)\n  ✔ 历史超限文件保持基线通过 (4.351083ms)\n  ✔ 历史文件增加一行失败 (3.466459ms)\n  ✔ 大目录基线通配被拒绝 (1.034833ms)\n  ✔ src 平放测试失败 (1.32925ms)\n  ✔ 无理由 suppress 失败 (1.007667ms)\n  ✔ 合格小文件通过 (0.628583ms)\n  ✔ validateBaselineDoc 拒绝通配 (0.075625ms)\n  ✔ 输出格式可被 path:line:col 解析 (3.336334ms)\n  ✔ 真实引擎包在基线下可过结构门禁 (113.078166ms)\n✔ check:engine-structure (149.923208ms)\nℹ tests 15\nℹ suites 1\nℹ pass 15\nℹ fail 0\nℹ cancelled 0\nℹ skipped 0\nℹ todo 0\nℹ duration_ms 288.946416\n\nquality:engine ok\n[gbx] ■ verify:npm run quality:engine done exit=0 elapsed=5s\n",
      "stderr": "",
      "stdoutTail": ".test.ts (1 test) 106ms\n ✓ tests/host/a-to-b-memory-e2e.test.ts (1 test) 120ms\n ✓ tests/host/chat-turns-e2e.test.ts (2 tests) 250ms\n ✓ tests/host/end-story-next-e2e.test.ts (1 test) 208ms\n ✓ tests/lore/bootstrap-fallback.test.ts (6 tests) 35ms\n ✓ tests/host/wet.test.ts (8 tests) 16ms\n ✓ tests/memory/sqlite-memory.test.ts (8 tests) 59ms\n ✓ tests/runtime/effect-sink-plan-status.test.ts (7 tests) 50ms\n ✓ tests/schedule/card-reference-and-classify.test.ts (9 tests) 5ms\n ✓ tests/runtime/effect-s11.test.ts (5 tests) 5ms\n ✓ tests/runtime/pick-pending-entry-mode.test.ts (4 tests) 3ms\n ✓ tests/runtime/end-story-cleanup.test.ts (5 tests) 6ms\n ✓ tests/runtime/select-call-flow-prompt.test.ts (2 tests) 2ms\n ✓ tests/runtime/composer.test.ts (6 tests) 5ms\n ✓ tests/runtime/composer.localHourRange.test.ts (7 tests) 6ms\n ✓ tests/schema/callcard-schema-tighten.test.ts (4 tests) 3ms\n ✓ tests/schema/user-schema.test.ts (4 tests) 3ms\n ✓ tests/host/log-redact.test.ts (1 test) 1ms\n ✓ tests/runtime/exit-selector.test.ts (3 tests) 1ms\n ✓ tests/index.smoke.test.ts (1 test) 1ms\n\n Test Files  38 passed (38)\n      Tests  144 passed (144)\n   Start at  19:42:29\n   Duration  3.04s (transform 941ms, setup 0ms, collect 8.22s, tests 5.53s, environment 5ms, prepare 1.88s)\n\n\n==> gate self-tests (engine-structure)\n▶ check:engine-structure\n  ✔ 有效行数忽略空行 (0.45275ms)\n  ✔ host 文件分类 (0.121583ms)\n  ✔ 圈复杂度统计分支 (3.227625ms)\n  ✔ 新文件超过文件硬上限失败 (12.705042ms)\n  ✔ 新函数超过函数硬上限失败 (2.754583ms)\n  ✔ 圈复杂度超过硬上限失败 (1.431458ms)\n  ✔ 历史超限文件保持基线通过 (4.351083ms)\n  ✔ 历史文件增加一行失败 (3.466459ms)\n  ✔ 大目录基线通配被拒绝 (1.034833ms)\n  ✔ src 平放测试失败 (1.32925ms)\n  ✔ 无理由 suppress 失败 (1.007667ms)\n  ✔ 合格小文件通过 (0.628583ms)\n  ✔ validateBaselineDoc 拒绝通配 (0.075625ms)\n  ✔ 输出格式可被 path:line:col 解析 (3.336334ms)\n  ✔ 真实引擎包在基线下可过结构门禁 (113.078166ms)\n✔ check:engine-structure (149.923208ms)\nℹ tests 15\nℹ suites 1\nℹ pass 15\nℹ fail 0\nℹ cancelled 0\nℹ skipped 0\nℹ todo 0\nℹ duration_ms 288.946416\n\nquality:engine ok\n[gbx] ■ verify:npm run quality:engine done exit=0 elapsed=5s\n",
      "stderrTail": "",
      "errorLocations": [
        {
          "file": "packages/rpg-engine/src/host",
          "line": 1,
          "column": 1,
          "code": "ENGINE-STRUCT-009",
          "message": "当前=8  允许=clustered-dirs  目录含 8 个源文件且职责组≥2（card,host,schedule,enginelogfile,errors,types,wet），应分子目录  按职责拆分子目录，禁止长前缀代目录；新增文件勿继续恶化平铺",
          "severity": "error"
        },
        {
          "file": "packages/rpg-engine/src/runtime",
          "line": 1,
          "column": 1,
          "code": "ENGINE-STRUCT-009",
          "message": "当前=12  允许=clustered-dirs  目录含 12 个源文件且职责组≥2（activestorylock,card,composescene,composer,effect,evaluatecondition,exitselector,pickpendingforuserdial,schedule），应分子目录  按职责拆分子目录，禁止长前缀代目录；新增文件勿继续恶化平铺",
          "severity": "error"
        },
        {
          "file": "packages/rpg-engine/src/schema",
          "line": 1,
          "column": 1,
          "code": "ENGINE-STRUCT-009",
          "message": "当前=10  允许=clustered-dirs  目录含 10 个源文件且职责组≥2（asset,card,character,host,outcome,persist,promptscene,schedule,worldfact,worldlore），应分子目录  按职责拆分子目录，禁止长前缀代目录；新增文件勿继续恶化平铺",
          "severity": "error"
        },
        {
          "file": "packages/rpg-engine/src/tools",
          "line": 1,
          "column": 1,
          "code": "ENGINE-STRUCT-009",
          "message": "当前=5  允许=clustered-dirs  目录含 5 个源文件且职责组≥2（builtinregistry,effect,host,resolvetoolpolicy,types），应分子目录  按职责拆分子目录，禁止长前缀代目录；新增文件勿继续恶化平铺",
          "severity": "error"
        },
        {
          "file": "packages/rpg-engine/src/host/createScheduleClockApi.ts",
          "line": 18,
          "column": 1,
          "code": "ENGINE-STRUCT-002",
          "message": "当前=95  允许=60  函数 createScheduleClockApi 有效行数 95 超过告警线 60  考虑拆分以保持可测性",
          "severity": "warn"
        },
        {
          "file": "packages/rpg-engine/src/host/createScheduleClockApi.ts",
          "line": 18,
          "column": 1,
          "code": "ENGINE-STRUCT-003",
          "message": "当前=11  允许=10  函数 createScheduleClockApi 圈复杂度 11 超过告警线 10  重构条件分支",
          "severity": "warn"
        },
        {
          "file": "packages/rpg-engine/src/host/wet.ts",
          "line": 140,
          "column": 1,
          "code": "ENGINE-STRUCT-003",
          "message": "当前=13  允许=10  函数 validateWetAppend 圈复杂度 13 超过告警线 10  重构条件分支",
          "severity": "warn"
        },
        {
          "file": "packages/rpg-engine/src/host/wet.ts",
          "line": 196,
          "column": 1,
          "code": "ENGINE-STRUCT-002",
          "message": "当前=62  允许=60  函数 buildWetReplayView 有效行数 62 超过告警线 60  考虑拆分以保持可测性",
          "severity": "warn"
        },
        {
          "file": "packages/rpg-engine/src/host/wet.ts",
          "line": 196,
          "column": 1,
          "code": "ENGINE-STRUCT-003",
          "message": "当前=12  允许=10  函数 buildWetReplayView 圈复杂度 12 超过告警线 10  重构条件分支",
          "severity": "warn"
        },
        {
          "file": "packages/rpg-engine/src/runtime/activeStoryLock.ts",
          "line": 28,
          "column": 1,
          "code": "ENGINE-STRUCT-003",
          "message": "当前=12  允许=10  函数 asStorySave 圈复杂度 12 超过告警线 10  重构条件分支",
          "severity": "warn"
        },
        {
          "file": "packages/rpg-engine/src/runtime/activeStoryLock.ts",
          "line": 62,
          "column": 1,
          "code": "ENGINE-STRUCT-003",
          "message": "当前=11  允许=10  函数 findActiveStoryLock 圈复杂度 11 超过告警线 10  重构条件分支",
          "severity": "warn"
        },
        {
          "file": "packages/rpg-engine/src/runtime/activeStoryLock.ts",
          "line": 153,
          "column": 1,
          "code": "ENGINE-STRUCT-003",
          "message": "当前=14  允许=10  函数 activateStoryOnBegin 圈复杂度 14 超过告警线 10  重构条件分支",
          "severity": "warn"
        },
        {
          "file": "packages/rpg-engine/src/runtime/classifyCall.ts",
          "line": 28,
          "column": 1,
          "code": "ENGINE-STRUCT-003",
          "message": "当前=14  允许=10  函数 classifyCall 圈复杂度 14 超过告警线 10  重构条件分支",
          "severity": "warn"
        },
        {
          "file": "packages/rpg-engine/src/runtime/evaluateCondition.ts",
          "line": 7,
          "column": 1,
          "code": "ENGINE-STRUCT-003",
          "message": "当前=11  允许=10  函数 evaluateExitCondition 圈复杂度 11 超过告警线 10  重构条件分支",
          "severity": "warn"
        },
        {
          "file": "packages/rpg-engine/src/runtime/exitSelector.ts",
          "line": 20,
          "column": 1,
          "code": "ENGINE-STRUCT-002",
          "message": "当前=69  允许=60  函数 selectExit 有效行数 69 超过告警线 60  考虑拆分以保持可测性",
          "severity": "warn"
        },
        {
          "file": "packages/rpg-engine/src/runtime/exitSelector.ts",
          "line": 20,
          "column": 1,
          "code": "ENGINE-STRUCT-003",
          "message": "当前=12  允许=10  函数 selectExit 圈复杂度 12 超过告警线 10  重构条件分支",
          "severity": "warn"
        },
        {
          "file": "packages/rpg-engine/src/runtime/freeCallPostPipeline.ts",
          "line": 37,
          "column": 1,
          "code": "ENGINE-STRUCT-002",
          "message": "当前=88  允许=60  函数 runFreeCallPostPipeline 有效行数 88 超过告警线 60  考虑拆分以保持可测性",
          "severity": "warn"
        },
        {
          "file": "packages/rpg-engine/src/runtime/freeCallPostPipeline.ts",
          "line": 37,
          "column": 1,
          "code": "ENGINE-STRUCT-003",
          "message": "当前=11  允许=10  函数 runFreeCallPostPipeline 圈复杂度 11 超过告警线 10  重构条件分支",
          "severity": "warn"
        },
        {
          "file": "packages/rpg-engine/src/runtime/pickPendingForUserDial.ts",
          "line": 56,
          "column": 1,
          "code": "ENGINE-STRUCT-003",
          "message": "当前=14  允许=10  函数 pickPendingForIntent 圈复杂度 14 超过告警线 10  重构条件分支",
          "severity": "warn"
        },
        {
          "file": "packages/rpg-engine/src/schedule/reconcileRecurringIntents.ts",
          "line": 41,
          "column": 1,
          "code": "ENGINE-STRUCT-003",
          "message": "当前=11  允许=10  函数 reconcileRecurringIntents 圈复杂度 11 超过告警线 10  重构条件分支",
          "severity": "warn"
        },
        {
          "file": "packages/rpg-engine/src/schedule/writeRecurringIntentFromEffect.ts",
          "line": 47,
          "column": 1,
          "code": "ENGINE-STRUCT-003",
          "message": "当前=11  允许=10  函数 writeRecurringIntentFromEffect 圈复杂度 11 超过告警线 10  重构条件分支",
          "severity": "warn"
        },
        {
          "file": "packages/rpg-engine/src/schema/promptScene.ts",
          "line": 63,
          "column": 1,
          "code": "ENGINE-STRUCT-003",
          "message": "当前=15  允许=10  函数 validatePromptScenePatches 圈复杂度 15 超过告警线 10  重构条件分支",
          "severity": "warn"
        },
        {
          "file": "packages/rpg-engine/src/tools/resolveToolPolicy.ts",
          "line": 8,
          "column": 1,
          "code": "ENGINE-STRUCT-003",
          "message": "当前=13  允许=10  函数 resolveToolPolicy 圈复杂度 13 超过告警线 10  重构条件分支",
          "severity": "warn"
        },
        {
          "file": "packages/rpg-engine/tests/host/a-to-b-memory-e2e.test.ts",
          "line": 17,
          "column": 38,
          "code": "ENGINE-STRUCT-002",
          "message": "当前=80  允许=60  函数 <anonymous> 有效行数 80 超过告警线 60  考虑拆分以保持可测性",
          "severity": "warn"
        },
        {
          "file": "packages/rpg-engine/tests/host/a-to-b-memory-e2e.test.ts",
          "line": 27,
          "column": 70,
          "code": "ENGINE-STRUCT-002",
          "message": "当前=71  允许=60  函数 <anonymous> 有效行数 71 超过告警线 60  考虑拆分以保持可测性",
          "severity": "warn"
        },
        {
          "file": "packages/rpg-engine/tests/host/chat-turns-e2e.test.ts",
          "line": 17,
          "column": 37,
          "code": "ENGINE-STRUCT-002",
          "message": "当前=91  允许=60  函数 <anonymous> 有效行数 91 超过告警线 60  考虑拆分以保持可测性",
          "severity": "warn"
        },
        {
          "file": "packages/rpg-engine/tests/host/chat-turns-e2e.test.ts",
          "line": 17,
          "column": 37,
          "code": "ENGINE-STRUCT-003",
          "message": "当前=13  允许=10  函数 <anonymous> 圈复杂度 13 超过告警线 10  重构条件分支",
          "severity": "warn"
        },
        {
          "file": "packages/rpg-engine/tests/host/manual-story-loop.test.ts",
          "line": 21,
          "column": 31,
          "code": "ENGINE-STRUCT-002",
          "message": "当前=86  允许=60  函数 <anonymous> 有效行数 86 超过告警线 60  考虑拆分以保持可测性",
          "severity": "warn"
        },
        {
          "file": "packages/rpg-engine/tests/host/night-layer-e2e.test.ts",
          "line": 17,
          "column": 40,
          "code": "ENGINE-STRUCT-002",
          "message": "当前=75  允许=60  函数 <anonymous> 有效行数 75 超过告警线 60  考虑拆分以保持可测性",
          "severity": "warn"
        },
        {
          "file": "packages/rpg-engine/tests/host/playback-phase.test.ts",
          "line": 20,
          "column": 40,
          "code": "ENGINE-STRUCT-002",
          "message": "当前=94  允许=60  函数 <anonymous> 有效行数 94 超过告警线 60  考虑拆分以保持可测性",
          "severity": "warn"
        },
        {
          "file": "packages/rpg-engine/tests/host/playback-phase.test.ts",
          "line": 30,
          "column": 79,
          "code": "ENGINE-STRUCT-002",
          "message": "当前=85  允许=60  函数 <anonymous> 有效行数 85 超过告警线 60  考虑拆分以保持可测性",
          "severity": "warn"
        },
        {
          "file": "packages/rpg-engine/tests/runtime/composer.localHourRange.test.ts",
          "line": 145,
          "column": 56,
          "code": "ENGINE-STRUCT-002",
          "message": "当前=80  允许=60  函数 <anonymous> 有效行数 80 超过告警线 60  考虑拆分以保持可测性",
          "severity": "warn"
        },
        {
          "file": "packages/rpg-engine/tests/runtime/pick-pending-entry-mode.test.ts",
          "line": 38,
          "column": 41,
          "code": "ENGINE-STRUCT-002",
          "message": "当前=86  允许=60  函数 <anonymous> 有效行数 86 超过告警线 60  考虑拆分以保持可测性",
          "severity": "warn"
        },
        {
          "file": "packages/rpg-engine/tests/schedule/card-reference-and-classify.test.ts",
          "line": 28,
          "column": 43,
          "code": "ENGINE-STRUCT-002",
          "message": "当前=81  允许=60  函数 <anonymous> 有效行数 81 超过告警线 60  考虑拆分以保持可测性",
          "severity": "warn"
        },
        {
          "file": "packages/rpg-engine/tests/schedule/card-reference-and-classify.test.ts",
          "line": 28,
          "column": 43,
          "code": "ENGINE-STRUCT-003",
          "message": "当前=14  允许=10  函数 <anonymous> 圈复杂度 14 超过告警线 10  重构条件分支",
          "severity": "warn"
        }
      ]
    },
    {
      "command": "npm run quality:studio",
      "exitCode": 0,
      "signal": null,
      "error": null,
      "stdout": "[gbx] ▶ verify:npm run quality:studio start cmd=/bin/sh cwd=/Users/bolbiao/workspace/airpc-engine\n\n> quality:studio\n> node scripts/studio-quality/quality-studio.mjs\n\n\n==> ensure-modal-layout (pre-typecheck)\nensure-modal-layout: nothing to remove\n\n==> ensure-migrated-layout (pre-typecheck)\nensure-migrated-layout: nothing to remove\n\n==> lint (@airpc/studio-v2)\n\n> @airpc/studio-v2@0.0.1 lint\n> node ./scripts/run-eslint.mjs . --max-warnings 0\n\n\n==> typecheck (@airpc/studio-v2)\n\n> @airpc/studio-v2@0.0.1 typecheck\n> tsc -p tsconfig.json --noEmit\n\n\n==> check:comments\ncheck:comments ok (198 files)\n\n==> check:studio-structure\nWARN STUDIO-STRUCT-003  apps/studioV2/app/api/characters/route.ts:54:1  函数 POST 圈复杂度 12 超过告警线 10  重构条件分支，避免继续堆叠\nWARN STUDIO-STRUCT-003  apps/studioV2/app/api/memory/route.ts:10:1  函数 GET 圈复杂度 11 超过告警线 10  重构条件分支，避免继续堆叠\nWARN STUDIO-STRUCT-001  apps/studioV2/src/bis/pageBis/characters/detail/form/characterDefMapper.ts:1:1  other 有效行数 377 超过告警线 350  尽快拆分，避免逼近硬上限\nWARN STUDIO-STRUCT-002  apps/studioV2/src/bis/pageBis/characters/detail/form/characterDefMapper.ts:150:1  函数 characterDefToSummary 有效行数 61 超过告警线 60  考虑拆分以保持可测性\nWARN STUDIO-STRUCT-002  apps/studioV2/src/bis/pageBis/characters/detail/form/characterDefMapper.ts:217:1  函数 mergeDetailFormIntoCharacterDef 有效行数 94 超过告警线 60  考虑拆分以保持可测性\nWARN STUDIO-STRUCT-002  apps/studioV2/src/bis/pageBis/characters/detail/form/characterDetailForm.ts:93:1  函数 applyCharacterDetailForm 有效行数 67 超过告警线 60  考虑拆分以保持可测性\nWARN STUDIO-STRUCT-003  apps/studioV2/src/bis/pageBis/characters/detail/form/characterDetailFormValidate.ts:125:1  函数 validateScenes 圈复杂度 13 超过告警线 10  重构条件分支，避免继续堆叠\nWARN STUDIO-STRUCT-002  apps/studioV2/src/commonUiComponents/form/blocks/AvatarUpload/index.tsx:19:5  函数 FormAvatarUpload 有效行数 72 超过告警线 60  考虑拆分以保持可测性\nWARN STUDIO-STRUCT-002  apps/studioV2/src/commonUiComponents/form/blocks/LocalHourRangeField/index.tsx:38:5  函数 FormLocalHourRangeField 有效行数 72 超过告警线 60  考虑拆分以保持可测性\nWARN STUDIO-STRUCT-002  apps/studioV2/src/commonUiComponents/form/blocks/PromptSceneListEditor/com/PromptSceneCardBody/index.tsx:34:2  函数 PromptSceneCardBody 有效行数 72 超过告警线 60  考虑拆分以保持可测性\nWARN STUDIO-STRUCT-002  apps/studioV2/src/commonUiComponents/form/blocks/PromptSceneListEditor/index.tsx:26:5  函数 FormPromptSceneListEditor 有效行数 65 超过告警线 60  考虑拆分以保持可测性\nWARN STUDIO-STRUCT-003  apps/studioV2/src/commonUiComponents/form/blocks/PromptSceneListEditor/promptSceneListHelpers.ts:26:1  函数 asPromptSceneList 圈复杂度 11 超过告警线 10  重构条件分支，避免继续堆叠\nWARN STUDIO-STRUCT-002  apps/studioV2/src/commonUiComponents/form/blocks/PromptVariantListEditor/index.tsx:36:5  函数 FormPromptVariantListEditor 有效行数 96 超过告警线 60  考虑拆分以保持可测性\nWARN STUDIO-STRUCT-002  apps/studioV2/src/commonUiComponents/form/blocks/StringListEditor/index.tsx:24:5  函数 FormStringListEditor 有效行数 72 超过告警线 60  考虑拆分以保持可测性\nWARN STUDIO-STRUCT-002  apps/studioV2/src/pageComponents/assets/com/AssetDetailEditForm.tsx:40:2  函数 AssetDetailEditForm 有效行数 68 超过告警线 60  考虑拆分以保持可测性\nWARN STUDIO-STRUCT-002  apps/studioV2/src/pageComponents/assets/hooks/useAssetLibraryPage.ts:19:1  函数 useAssetLibraryPage 有效行数 78 超过告警线 60  考虑拆分以保持可测性\nWARN STUDIO-STRUCT-003  apps/studioV2/src/pageComponents/assets/hooks/useAssetLibraryPage.ts:19:1  函数 useAssetLibraryPage 圈复杂度 11 超过告警线 10  重构条件分支，避免继续堆叠\nWARN STUDIO-STRUCT-002  apps/studioV2/src/pageComponents/characters/CharacterLibraryView.tsx:22:41  函数 CharacterLibraryView 有效行数 82 超过告警线 60  考虑拆分以保持可测性\nWARN STUDIO-STRUCT-002  apps/studioV2/src/pageComponents/characters/com/CharacterDetailEditForm.tsx:39:2  函数 CharacterDetailEditForm 有效行数 67 超过告警线 60  考虑拆分以保持可测性\nWARN STUDIO-STRUCT-002  apps/studioV2/src/pageComponents/characters/com/memory/CharacterMemoryMainBody.tsx:48:5  函数 CharacterMemoryMainBody 有效行数 62 超过告警线 60  考虑拆分以保持可测性\nWARN STUDIO-STRUCT-002  apps/studioV2/src/pageComponents/characters/hooks/useCharacterLibraryPage.ts:18:1  函数 useCharacterLibraryPage 有效行数 98 超过告警线 60  考虑拆分以保持可测性\nWARN STUDIO-STRUCT-003  apps/studioV2/src/pageComponents/characters/hooks/useCharacterLibraryPage.ts:18:1  函数 useCharacterLibraryPage 圈复杂度 15 超过告警线 10  重构条件分支，避免继续堆叠\nWARN STUDIO-STRUCT-002  apps/studioV2/src/pageComponents/debugger/com/CallRunPanel.tsx:43:52  函数 CallRunPanel 有效行数 72 超过告警线 60  考虑拆分以保持可测性\nWARN STUDIO-STRUCT-002  apps/studioV2/src/pageComponents/home/WorkbenchSideCol.tsx:21:37  函数 WorkbenchSideCol 有效行数 78 超过告警线 60  考虑拆分以保持可测性\nWARN STUDIO-STRUCT-002  apps/studioV2/src/pageComponents/packages/create/CreatePackageView.tsx:23:38  函数 CreatePackageView 有效行数 71 超过告警线 60  考虑拆分以保持可测性\nWARN STUDIO-STRUCT-002  apps/studioV2/src/pageComponents/packages/export/ExportPackageForm.tsx:33:45  函数 ExportPackageForm 有效行数 65 超过告警线 60  考虑拆分以保持可测性\nWARN STUDIO-STRUCT-002  apps/studioV2/src/pageComponents/packages/list/PackageListView.tsx:34:36  函数 PackageListView 有效行数 93 超过告警线 60  考虑拆分以保持可测性\nWARN STUDIO-STRUCT-002  apps/studioV2/src/pageComponents/settings/com/SettingsEnginePanels.tsx:92:62  函数 SchemaEnginePanel 有效行数 65 超过告警线 60  考虑拆分以保持可测性\nWARN STUDIO-STRUCT-002  apps/studioV2/src/pageComponents/storyEditor/StoryEditorShell.tsx:36:60  函数 StoryEditorShell 有效行数 95 超过告警线 60  考虑拆分以保持可测性\nWARN STUDIO-STRUCT-002  apps/studioV2/src/pageComponents/storyEditor/canvas/useStoryCanvasGraph.ts:54:1  函数 useStoryCanvasGraph 有效行数 98 超过告警线 60  考虑拆分以保持可测性\nWARN STUDIO-STRUCT-002  apps/studioV2/src/pageComponents/storyEditor/com/panel/NodePropertyForm.tsx:41:2  函数 NodePropertyForm 有效行数 91 超过告警线 60  考虑拆分以保持可测性\nWARN STUDIO-STRUCT-002  apps/studioV2/src/pageComponents/users/UserLibraryView.tsx:41:36  函数 UserLibraryView 有效行数 67 超过告警线 60  考虑拆分以保持可测性\nWARN STUDIO-STRUCT-002  apps/studioV2/src/pageComponents/users/com/UserDetailEditForm.tsx:40:2  函数 UserDetailEditForm 有效行数 67 超过告警线 60  考虑拆分以保持可测性\nWARN STUDIO-STRUCT-002  apps/studioV2/src/pageComponents/users/hooks/useUserLibraryPage.ts:18:1  函数 useUserLibraryPage 有效行数 69 超过告警线 60  考虑拆分以保持可测性\nWARN STUDIO-STRUCT-003  apps/studioV2/src/utils/server/http/apiResponse.server.ts:23:1  函数 httpStatusForCode 圈复杂度 12 超过告警线 10  重构条件分支，避免继续堆叠\ncheck:studio-structure ok (198 files, 35 warnings)\n\n==> test:studio\n\n> test:studio\n> npm run test -w @airpc/studio-v2\n\n\n> @airpc/studio-v2@0.0.1 test\n> vitest run\n\n\n RUN  v3.2.7 /Users/bolbiao/workspace/airpc-engine/apps/studioV2\n\n ✓ tests/commonUi/modalContract.test.ts (3 tests) 2ms\n ✓ tests/commonUi/paginationSlice.test.ts (5 tests) 2ms\n ✓ tests/characters/characterDefMapper.test.ts (3 tests) 5ms\n ✓ tests/characters/characterForm.test.ts (5 tests) 6ms\n ✓ tests/assets/assetForm.test.ts (8 tests) 5ms\n ✓ tests/characters/createFormItems.test.ts (3 tests) 2ms\n ✓ tests/packages/createPackageForm.test.ts (2 tests) 2ms\n ✓ tests/domain/createStudioId.test.ts (2 tests) 5ms\n ✓ tests/storyEditor/mockEditorCharacters.test.ts (5 tests) 3ms\n ✓ tests/users/userForm.test.ts (7 tests) 5ms\n ✓ tests/storyEditor/nodePropertyAndRole.test.ts (4 tests) 4ms\n ✓ tests/commonUi/formFieldConfig.test.ts (5 tests) 8ms\n ↓ tests/tmp-remove-flat-prompt-scene.test.ts (1 test | 1 skipped)\n ✓ tests/commonUi/autoFormContract.test.ts (8 tests) 4ms\n\n Test Files  13 passed | 1 skipped (14)\n      Tests  60 passed | 1 skipped (61)\n   Start at  19:42:37\n   Duration  951ms (transform 604ms, setup 0ms, collect 1.54s, tests 53ms, environment 2ms, prepare 777ms)\n\n\n==> gate self-tests (comments + structure)\n▶ check:comments\n  ✔ 合格契约通过 (9.720541ms)\n  ✔ 缺失导出意图注释失败 (2.054625ms)\n  ✔ 缺失字段说明失败 (1.149792ms)\n  ✔ 复述占位注释失败 (1.1615ms)\n  ✔ 无原因抑制失败（含裸 eslint-disable） (2.648958ms)\n  ✔ 带原因抑制通过 (1.411792ms)\n  ✔ 输出格式含规则编号与位置 (1.207709ms)\n✔ check:comments (20.055375ms)\n▶ check:studio-structure\n  ✔ 有效行数忽略空行但不忽略注释 (0.537959ms)\n  ✔ page.tsx 分类正确 (0.152625ms)\n  ✔ 圈复杂度统计分支 (3.519459ms)\n  ✔ 合格基线通过，且排除 generated (9.228208ms)\n  ✔ page 行数硬上限失败 (3.308375ms)\n  ✔ 函数复杂度硬上限失败 (2.703708ms)\n  ✔ client 引擎写口失败 (2.9145ms)\n  ✔ 业务旁平放测试失败 (3.447833ms)\n  ✔ 深挖引擎内部路径失败 (1.621666ms)\n  ✔ 目录异责平铺失败 (3.108458ms)\n  ✔ 业务 barrel index 失败 (1.226625ms)\n  ✔ 旧式顶层业务目录失败 (1.5735ms)\n  ✔ 兼容转发壳失败 (2.511041ms)\n  ✔ 同一语义区重复入口失败 (2.033708ms)\n  ✔ commonUiComponents 平铺组件失败 (2.4035ms)\n  ✔ 新增或修改代码使用空格缩进失败 (3.246542ms)\n  ✔ 自定义组件引用缺少用途注释失败 (1.972958ms)\n  ✔ 组件 props 未在入口显式解构失败 (1.88175ms)\n  ✔ 入口格式合格通过 (2.177875ms)\n  ✔ UI 组件裸 fetch 失败 (1.73725ms)\n  ✔ 大范围豁免被拒绝 (1.24075ms)\n  ✔ 精确豁免生效 (2.111584ms)\n  ✔ validateAllowlist 拒绝 apps/** (0.09625ms)\n  ✔ 输出格式含规则编号与位置（路径可定位） (1.643958ms)\n✔ check:studio-structure (57.491834ms)\nℹ tests 31\nℹ suites 2\nℹ pass 31\nℹ fail 0\nℹ cancelled 0\nℹ skipped 0\nℹ todo 0\nℹ duration_ms 198.116625\n\nquality:studio ok\n[gbx] ■ verify:npm run quality:studio done exit=0 elapsed=6s\n",
      "stderr": "",
      "stdoutTail": "ts:18:1  函数 useCharacterLibraryPage 圈复杂度 15 超过告警线 10  重构条件分支，避免继续堆叠\nWARN STUDIO-STRUCT-002  apps/studioV2/src/pageComponents/debugger/com/CallRunPanel.tsx:43:52  函数 CallRunPanel 有效行数 72 超过告警线 60  考虑拆分以保持可测性\nWARN STUDIO-STRUCT-002  apps/studioV2/src/pageComponents/home/WorkbenchSideCol.tsx:21:37  函数 WorkbenchSideCol 有效行数 78 超过告警线 60  考虑拆分以保持可测性\nWARN STUDIO-STRUCT-002  apps/studioV2/src/pageComponents/packages/create/CreatePackageView.tsx:23:38  函数 CreatePackageView 有效行数 71 超过告警线 60  考虑拆分以保持可测性\nWARN STUDIO-STRUCT-002  apps/studioV2/src/pageComponents/packages/export/ExportPackageForm.tsx:33:45  函数 ExportPackageForm 有效行数 65 超过告警线 60  考虑拆分以保持可测性\nWARN STUDIO-STRUCT-002  apps/studioV2/src/pageComponents/packages/list/PackageListView.tsx:34:36  函数 PackageListView 有效行数 93 超过告警线 60  考虑拆分以保持可测性\nWARN STUDIO-STRUCT-002  apps/studioV2/src/pageComponents/settings/com/SettingsEnginePanels.tsx:92:62  函数 SchemaEnginePanel 有效行数 65 超过告警线 60  考虑拆分以保持可测性\nWARN STUDIO-STRUCT-002  apps/studioV2/src/pageComponents/storyEditor/StoryEditorShell.tsx:36:60  函数 StoryEditorShell 有效行数 95 超过告警线 60  考虑拆分以保持可测性\nWARN STUDIO-STRUCT-002  apps/studioV2/src/pageComponents/storyEditor/canvas/useStoryCanvasGraph.ts:54:1  函数 useStoryCanvasGraph 有效行数 98 超过告警线 60  考虑拆分以保持可测性\nWARN STUDIO-STRUCT-002  apps/studioV2/src/pageComponents/storyEditor/com/panel/NodePropertyForm.tsx:41:2  函数 NodePropertyForm 有效行数 91 超过告警线 60  考虑拆分以保持可测性\nWARN STUDIO-STRUCT-002  apps/studioV2/src/pageComponents/users/UserLibraryView.tsx:41:36  函数 UserLibraryView 有效行数 67 超过告警线 60  考虑拆分以保持可测性\nWARN STUDIO-STRUCT-002  apps/studioV2/src/pageComponents/users/com/UserDetailEditForm.tsx:40:2  函数 UserDetailEditForm 有效行数 67 超过告警线 60  考虑拆分以保持可测性\nWARN STUDIO-STRUCT-002  apps/studioV2/src/pageComponents/users/hooks/useUserLibraryPage.ts:18:1  函数 useUserLibraryPage 有效行数 69 超过告警线 60  考虑拆分以保持可测性\nWARN STUDIO-STRUCT-003  apps/studioV2/src/utils/server/http/apiResponse.server.ts:23:1  函数 httpStatusForCode 圈复杂度 12 超过告警线 10  重构条件分支，避免继续堆叠\ncheck:studio-structure ok (198 files, 35 warnings)\n\n==> test:studio\n\n> test:studio\n> npm run test -w @airpc/studio-v2\n\n\n> @airpc/studio-v2@0.0.1 test\n> vitest run\n\n\n RUN  v3.2.7 /Users/bolbiao/workspace/airpc-engine/apps/studioV2\n\n ✓ tests/commonUi/modalContract.test.ts (3 tests) 2ms\n ✓ tests/commonUi/paginationSlice.test.ts (5 tests) 2ms\n ✓ tests/characters/characterDefMapper.test.ts (3 tests) 5ms\n ✓ tests/characters/characterForm.test.ts (5 tests) 6ms\n ✓ tests/assets/assetForm.test.ts (8 tests) 5ms\n ✓ tests/characters/createFormItems.test.ts (3 tests) 2ms\n ✓ tests/packages/createPackageForm.test.ts (2 tests) 2ms\n ✓ tests/domain/createStudioId.test.ts (2 tests) 5ms\n ✓ tests/storyEditor/mockEditorCharacters.test.ts (5 tests) 3ms\n ✓ tests/users/userForm.test.ts (7 tests) 5ms\n ✓ tests/storyEditor/nodePropertyAndRole.test.ts (4 tests) 4ms\n ✓ tests/commonUi/formFieldConfig.test.ts (5 tests) 8ms\n ↓ tests/tmp-remove-flat-prompt-scene.test.ts (1 test | 1 skipped)\n ✓ tests/commonUi/autoFormContract.test.ts (8 tests) 4ms\n\n Test Files  13 passed | 1 skipped (14)\n      Tests  60 passed | 1 skipped (61)\n   Start at  19:42:37\n   Duration  951ms (transform 604ms, setup 0ms, collect 1.54s, tests 53ms, environment 2ms, prepare 777ms)\n\n\n==> gate self-tests (comments + structure)\n▶ check:comments\n  ✔ 合格契约通过 (9.720541ms)\n  ✔ 缺失导出意图注释失败 (2.054625ms)\n  ✔ 缺失字段说明失败 (1.149792ms)\n  ✔ 复述占位注释失败 (1.1615ms)\n  ✔ 无原因抑制失败（含裸 eslint-disable） (2.648958ms)\n  ✔ 带原因抑制通过 (1.411792ms)\n  ✔ 输出格式含规则编号与位置 (1.207709ms)\n✔ check:comments (20.055375ms)\n▶ check:studio-structure\n  ✔ 有效行数忽略空行但不忽略注释 (0.537959ms)\n  ✔ page.tsx 分类正确 (0.152625ms)\n  ✔ 圈复杂度统计分支 (3.519459ms)\n  ✔ 合格基线通过，且排除 generated (9.228208ms)\n  ✔ page 行数硬上限失败 (3.308375ms)\n  ✔ 函数复杂度硬上限失败 (2.703708ms)\n  ✔ client 引擎写口失败 (2.9145ms)\n  ✔ 业务旁平放测试失败 (3.447833ms)\n  ✔ 深挖引擎内部路径失败 (1.621666ms)\n  ✔ 目录异责平铺失败 (3.108458ms)\n  ✔ 业务 barrel index 失败 (1.226625ms)\n  ✔ 旧式顶层业务目录失败 (1.5735ms)\n  ✔ 兼容转发壳失败 (2.511041ms)\n  ✔ 同一语义区重复入口失败 (2.033708ms)\n  ✔ commonUiComponents 平铺组件失败 (2.4035ms)\n  ✔ 新增或修改代码使用空格缩进失败 (3.246542ms)\n  ✔ 自定义组件引用缺少用途注释失败 (1.972958ms)\n  ✔ 组件 props 未在入口显式解构失败 (1.88175ms)\n  ✔ 入口格式合格通过 (2.177875ms)\n  ✔ UI 组件裸 fetch 失败 (1.73725ms)\n  ✔ 大范围豁免被拒绝 (1.24075ms)\n  ✔ 精确豁免生效 (2.111584ms)\n  ✔ validateAllowlist 拒绝 apps/** (0.09625ms)\n  ✔ 输出格式含规则编号与位置（路径可定位） (1.643958ms)\n✔ check:studio-structure (57.491834ms)\nℹ tests 31\nℹ suites 2\nℹ pass 31\nℹ fail 0\nℹ cancelled 0\nℹ skipped 0\nℹ todo 0\nℹ duration_ms 198.116625\n\nquality:studio ok\n[gbx] ■ verify:npm run quality:studio done exit=0 elapsed=6s\n",
      "stderrTail": "",
      "errorLocations": [
        {
          "file": "apps/studioV2/app/api/characters/route.ts",
          "line": 54,
          "column": 1,
          "code": "STUDIO-STRUCT-003",
          "message": "函数 POST 圈复杂度 12 超过告警线 10  重构条件分支，避免继续堆叠",
          "severity": "warn"
        },
        {
          "file": "apps/studioV2/app/api/memory/route.ts",
          "line": 10,
          "column": 1,
          "code": "STUDIO-STRUCT-003",
          "message": "函数 GET 圈复杂度 11 超过告警线 10  重构条件分支，避免继续堆叠",
          "severity": "warn"
        },
        {
          "file": "apps/studioV2/src/bis/pageBis/characters/detail/form/characterDefMapper.ts",
          "line": 1,
          "column": 1,
          "code": "STUDIO-STRUCT-001",
          "message": "other 有效行数 377 超过告警线 350  尽快拆分，避免逼近硬上限",
          "severity": "warn"
        },
        {
          "file": "apps/studioV2/src/bis/pageBis/characters/detail/form/characterDefMapper.ts",
          "line": 150,
          "column": 1,
          "code": "STUDIO-STRUCT-002",
          "message": "函数 characterDefToSummary 有效行数 61 超过告警线 60  考虑拆分以保持可测性",
          "severity": "warn"
        },
        {
          "file": "apps/studioV2/src/bis/pageBis/characters/detail/form/characterDefMapper.ts",
          "line": 217,
          "column": 1,
          "code": "STUDIO-STRUCT-002",
          "message": "函数 mergeDetailFormIntoCharacterDef 有效行数 94 超过告警线 60  考虑拆分以保持可测性",
          "severity": "warn"
        },
        {
          "file": "apps/studioV2/src/bis/pageBis/characters/detail/form/characterDetailForm.ts",
          "line": 93,
          "column": 1,
          "code": "STUDIO-STRUCT-002",
          "message": "函数 applyCharacterDetailForm 有效行数 67 超过告警线 60  考虑拆分以保持可测性",
          "severity": "warn"
        },
        {
          "file": "apps/studioV2/src/bis/pageBis/characters/detail/form/characterDetailFormValidate.ts",
          "line": 125,
          "column": 1,
          "code": "STUDIO-STRUCT-003",
          "message": "函数 validateScenes 圈复杂度 13 超过告警线 10  重构条件分支，避免继续堆叠",
          "severity": "warn"
        },
        {
          "file": "apps/studioV2/src/commonUiComponents/form/blocks/AvatarUpload/index.tsx",
          "line": 19,
          "column": 5,
          "code": "STUDIO-STRUCT-002",
          "message": "函数 FormAvatarUpload 有效行数 72 超过告警线 60  考虑拆分以保持可测性",
          "severity": "warn"
        },
        {
          "file": "apps/studioV2/src/commonUiComponents/form/blocks/LocalHourRangeField/index.tsx",
          "line": 38,
          "column": 5,
          "code": "STUDIO-STRUCT-002",
          "message": "函数 FormLocalHourRangeField 有效行数 72 超过告警线 60  考虑拆分以保持可测性",
          "severity": "warn"
        },
        {
          "file": "apps/studioV2/src/commonUiComponents/form/blocks/PromptSceneListEditor/com/PromptSceneCardBody/index.tsx",
          "line": 34,
          "column": 2,
          "code": "STUDIO-STRUCT-002",
          "message": "函数 PromptSceneCardBody 有效行数 72 超过告警线 60  考虑拆分以保持可测性",
          "severity": "warn"
        },
        {
          "file": "apps/studioV2/src/commonUiComponents/form/blocks/PromptSceneListEditor/index.tsx",
          "line": 26,
          "column": 5,
          "code": "STUDIO-STRUCT-002",
          "message": "函数 FormPromptSceneListEditor 有效行数 65 超过告警线 60  考虑拆分以保持可测性",
          "severity": "warn"
        },
        {
          "file": "apps/studioV2/src/commonUiComponents/form/blocks/PromptSceneListEditor/promptSceneListHelpers.ts",
          "line": 26,
          "column": 1,
          "code": "STUDIO-STRUCT-003",
          "message": "函数 asPromptSceneList 圈复杂度 11 超过告警线 10  重构条件分支，避免继续堆叠",
          "severity": "warn"
        },
        {
          "file": "apps/studioV2/src/commonUiComponents/form/blocks/PromptVariantListEditor/index.tsx",
          "line": 36,
          "column": 5,
          "code": "STUDIO-STRUCT-002",
          "message": "函数 FormPromptVariantListEditor 有效行数 96 超过告警线 60  考虑拆分以保持可测性",
          "severity": "warn"
        },
        {
          "file": "apps/studioV2/src/commonUiComponents/form/blocks/StringListEditor/index.tsx",
          "line": 24,
          "column": 5,
          "code": "STUDIO-STRUCT-002",
          "message": "函数 FormStringListEditor 有效行数 72 超过告警线 60  考虑拆分以保持可测性",
          "severity": "warn"
        },
        {
          "file": "apps/studioV2/src/pageComponents/assets/com/AssetDetailEditForm.tsx",
          "line": 40,
          "column": 2,
          "code": "STUDIO-STRUCT-002",
          "message": "函数 AssetDetailEditForm 有效行数 68 超过告警线 60  考虑拆分以保持可测性",
          "severity": "warn"
        },
        {
          "file": "apps/studioV2/src/pageComponents/assets/hooks/useAssetLibraryPage.ts",
          "line": 19,
          "column": 1,
          "code": "STUDIO-STRUCT-002",
          "message": "函数 useAssetLibraryPage 有效行数 78 超过告警线 60  考虑拆分以保持可测性",
          "severity": "warn"
        },
        {
          "file": "apps/studioV2/src/pageComponents/assets/hooks/useAssetLibraryPage.ts",
          "line": 19,
          "column": 1,
          "code": "STUDIO-STRUCT-003",
          "message": "函数 useAssetLibraryPage 圈复杂度 11 超过告警线 10  重构条件分支，避免继续堆叠",
          "severity": "warn"
        },
        {
          "file": "apps/studioV2/src/pageComponents/characters/CharacterLibraryView.tsx",
          "line": 22,
          "column": 41,
          "code": "STUDIO-STRUCT-002",
          "message": "函数 CharacterLibraryView 有效行数 82 超过告警线 60  考虑拆分以保持可测性",
          "severity": "warn"
        },
        {
          "file": "apps/studioV2/src/pageComponents/characters/com/CharacterDetailEditForm.tsx",
          "line": 39,
          "column": 2,
          "code": "STUDIO-STRUCT-002",
          "message": "函数 CharacterDetailEditForm 有效行数 67 超过告警线 60  考虑拆分以保持可测性",
          "severity": "warn"
        },
        {
          "file": "apps/studioV2/src/pageComponents/characters/com/memory/CharacterMemoryMainBody.tsx",
          "line": 48,
          "column": 5,
          "code": "STUDIO-STRUCT-002",
          "message": "函数 CharacterMemoryMainBody 有效行数 62 超过告警线 60  考虑拆分以保持可测性",
          "severity": "warn"
        },
        {
          "file": "apps/studioV2/src/pageComponents/characters/hooks/useCharacterLibraryPage.ts",
          "line": 18,
          "column": 1,
          "code": "STUDIO-STRUCT-002",
          "message": "函数 useCharacterLibraryPage 有效行数 98 超过告警线 60  考虑拆分以保持可测性",
          "severity": "warn"
        },
        {
          "file": "apps/studioV2/src/pageComponents/characters/hooks/useCharacterLibraryPage.ts",
          "line": 18,
          "column": 1,
          "code": "STUDIO-STRUCT-003",
          "message": "函数 useCharacterLibraryPage 圈复杂度 15 超过告警线 10  重构条件分支，避免继续堆叠",
          "severity": "warn"
        },
        {
          "file": "apps/studioV2/src/pageComponents/debugger/com/CallRunPanel.tsx",
          "line": 43,
          "column": 52,
          "code": "STUDIO-STRUCT-002",
          "message": "函数 CallRunPanel 有效行数 72 超过告警线 60  考虑拆分以保持可测性",
          "severity": "warn"
        },
        {
          "file": "apps/studioV2/src/pageComponents/home/WorkbenchSideCol.tsx",
          "line": 21,
          "column": 37,
          "code": "STUDIO-STRUCT-002",
          "message": "函数 WorkbenchSideCol 有效行数 78 超过告警线 60  考虑拆分以保持可测性",
          "severity": "warn"
        },
        {
          "file": "apps/studioV2/src/pageComponents/packages/create/CreatePackageView.tsx",
          "line": 23,
          "column": 38,
          "code": "STUDIO-STRUCT-002",
          "message": "函数 CreatePackageView 有效行数 71 超过告警线 60  考虑拆分以保持可测性",
          "severity": "warn"
        },
        {
          "file": "apps/studioV2/src/pageComponents/packages/export/ExportPackageForm.tsx",
          "line": 33,
          "column": 45,
          "code": "STUDIO-STRUCT-002",
          "message": "函数 ExportPackageForm 有效行数 65 超过告警线 60  考虑拆分以保持可测性",
          "severity": "warn"
        },
        {
          "file": "apps/studioV2/src/pageComponents/packages/list/PackageListView.tsx",
          "line": 34,
          "column": 36,
          "code": "STUDIO-STRUCT-002",
          "message": "函数 PackageListView 有效行数 93 超过告警线 60  考虑拆分以保持可测性",
          "severity": "warn"
        },
        {
          "file": "apps/studioV2/src/pageComponents/settings/com/SettingsEnginePanels.tsx",
          "line": 92,
          "column": 62,
          "code": "STUDIO-STRUCT-002",
          "message": "函数 SchemaEnginePanel 有效行数 65 超过告警线 60  考虑拆分以保持可测性",
          "severity": "warn"
        },
        {
          "file": "apps/studioV2/src/pageComponents/storyEditor/StoryEditorShell.tsx",
          "line": 36,
          "column": 60,
          "code": "STUDIO-STRUCT-002",
          "message": "函数 StoryEditorShell 有效行数 95 超过告警线 60  考虑拆分以保持可测性",
          "severity": "warn"
        },
        {
          "file": "apps/studioV2/src/pageComponents/storyEditor/canvas/useStoryCanvasGraph.ts",
          "line": 54,
          "column": 1,
          "code": "STUDIO-STRUCT-002",
          "message": "函数 useStoryCanvasGraph 有效行数 98 超过告警线 60  考虑拆分以保持可测性",
          "severity": "warn"
        },
        {
          "file": "apps/studioV2/src/pageComponents/storyEditor/com/panel/NodePropertyForm.tsx",
          "line": 41,
          "column": 2,
          "code": "STUDIO-STRUCT-002",
          "message": "函数 NodePropertyForm 有效行数 91 超过告警线 60  考虑拆分以保持可测性",
          "severity": "warn"
        },
        {
          "file": "apps/studioV2/src/pageComponents/users/UserLibraryView.tsx",
          "line": 41,
          "column": 36,
          "code": "STUDIO-STRUCT-002",
          "message": "函数 UserLibraryView 有效行数 67 超过告警线 60  考虑拆分以保持可测性",
          "severity": "warn"
        },
        {
          "file": "apps/studioV2/src/pageComponents/users/com/UserDetailEditForm.tsx",
          "line": 40,
          "column": 2,
          "code": "STUDIO-STRUCT-002",
          "message": "函数 UserDetailEditForm 有效行数 67 超过告警线 60  考虑拆分以保持可测性",
          "severity": "warn"
        },
        {
          "file": "apps/studioV2/src/pageComponents/users/hooks/useUserLibraryPage.ts",
          "line": 18,
          "column": 1,
          "code": "STUDIO-STRUCT-002",
          "message": "函数 useUserLibraryPage 有效行数 69 超过告警线 60  考虑拆分以保持可测性",
          "severity": "warn"
        },
        {
          "file": "apps/studioV2/src/utils/server/http/apiResponse.server.ts",
          "line": 23,
          "column": 1,
          "code": "STUDIO-STRUCT-003",
          "message": "函数 httpStatusForCode 圈复杂度 12 超过告警线 10  重构条件分支，避免继续堆叠",
          "severity": "warn"
        }
      ]
    }
  ],
  "errorLocations": [
    {
      "file": "packages/rpg-engine/src/host",
      "line": 1,
      "column": 1,
      "code": "ENGINE-STRUCT-009",
      "message": "当前=8  允许=clustered-dirs  目录含 8 个源文件且职责组≥2（card,host,schedule,enginelogfile,errors,types,wet），应分子目录  按职责拆分子目录，禁止长前缀代目录；新增文件勿继续恶化平铺",
      "severity": "error"
    },
    {
      "file": "packages/rpg-engine/src/runtime",
      "line": 1,
      "column": 1,
      "code": "ENGINE-STRUCT-009",
      "message": "当前=12  允许=clustered-dirs  目录含 12 个源文件且职责组≥2（activestorylock,card,composescene,composer,effect,evaluatecondition,exitselector,pickpendingforuserdial,schedule），应分子目录  按职责拆分子目录，禁止长前缀代目录；新增文件勿继续恶化平铺",
      "severity": "error"
    },
    {
      "file": "packages/rpg-engine/src/schema",
      "line": 1,
      "column": 1,
      "code": "ENGINE-STRUCT-009",
      "message": "当前=10  允许=clustered-dirs  目录含 10 个源文件且职责组≥2（asset,card,character,host,outcome,persist,promptscene,schedule,worldfact,worldlore），应分子目录  按职责拆分子目录，禁止长前缀代目录；新增文件勿继续恶化平铺",
      "severity": "error"
    },
    {
      "file": "packages/rpg-engine/src/tools",
      "line": 1,
      "column": 1,
      "code": "ENGINE-STRUCT-009",
      "message": "当前=5  允许=clustered-dirs  目录含 5 个源文件且职责组≥2（builtinregistry,effect,host,resolvetoolpolicy,types），应分子目录  按职责拆分子目录，禁止长前缀代目录；新增文件勿继续恶化平铺",
      "severity": "error"
    },
    {
      "file": "packages/rpg-engine/src/host/createScheduleClockApi.ts",
      "line": 18,
      "column": 1,
      "code": "ENGINE-STRUCT-002",
      "message": "当前=95  允许=60  函数 createScheduleClockApi 有效行数 95 超过告警线 60  考虑拆分以保持可测性",
      "severity": "warn"
    },
    {
      "file": "packages/rpg-engine/src/host/createScheduleClockApi.ts",
      "line": 18,
      "column": 1,
      "code": "ENGINE-STRUCT-003",
      "message": "当前=11  允许=10  函数 createScheduleClockApi 圈复杂度 11 超过告警线 10  重构条件分支",
      "severity": "warn"
    },
    {
      "file": "packages/rpg-engine/src/host/wet.ts",
      "line": 140,
      "column": 1,
      "code": "ENGINE-STRUCT-003",
      "message": "当前=13  允许=10  函数 validateWetAppend 圈复杂度 13 超过告警线 10  重构条件分支",
      "severity": "warn"
    },
    {
      "file": "packages/rpg-engine/src/host/wet.ts",
      "line": 196,
      "column": 1,
      "code": "ENGINE-STRUCT-002",
      "message": "当前=62  允许=60  函数 buildWetReplayView 有效行数 62 超过告警线 60  考虑拆分以保持可测性",
      "severity": "warn"
    },
    {
      "file": "packages/rpg-engine/src/host/wet.ts",
      "line": 196,
      "column": 1,
      "code": "ENGINE-STRUCT-003",
      "message": "当前=12  允许=10  函数 buildWetReplayView 圈复杂度 12 超过告警线 10  重构条件分支",
      "severity": "warn"
    },
    {
      "file": "packages/rpg-engine/src/runtime/activeStoryLock.ts",
      "line": 28,
      "column": 1,
      "code": "ENGINE-STRUCT-003",
      "message": "当前=12  允许=10  函数 asStorySave 圈复杂度 12 超过告警线 10  重构条件分支",
      "severity": "warn"
    },
    {
      "file": "packages/rpg-engine/src/runtime/activeStoryLock.ts",
      "line": 62,
      "column": 1,
      "code": "ENGINE-STRUCT-003",
      "message": "当前=11  允许=10  函数 findActiveStoryLock 圈复杂度 11 超过告警线 10  重构条件分支",
      "severity": "warn"
    },
    {
      "file": "packages/rpg-engine/src/runtime/activeStoryLock.ts",
      "line": 153,
      "column": 1,
      "code": "ENGINE-STRUCT-003",
      "message": "当前=14  允许=10  函数 activateStoryOnBegin 圈复杂度 14 超过告警线 10  重构条件分支",
      "severity": "warn"
    },
    {
      "file": "packages/rpg-engine/src/runtime/classifyCall.ts",
      "line": 28,
      "column": 1,
      "code": "ENGINE-STRUCT-003",
      "message": "当前=14  允许=10  函数 classifyCall 圈复杂度 14 超过告警线 10  重构条件分支",
      "severity": "warn"
    },
    {
      "file": "packages/rpg-engine/src/runtime/evaluateCondition.ts",
      "line": 7,
      "column": 1,
      "code": "ENGINE-STRUCT-003",
      "message": "当前=11  允许=10  函数 evaluateExitCondition 圈复杂度 11 超过告警线 10  重构条件分支",
      "severity": "warn"
    },
    {
      "file": "packages/rpg-engine/src/runtime/exitSelector.ts",
      "line": 20,
      "column": 1,
      "code": "ENGINE-STRUCT-002",
      "message": "当前=69  允许=60  函数 selectExit 有效行数 69 超过告警线 60  考虑拆分以保持可测性",
      "severity": "warn"
    },
    {
      "file": "packages/rpg-engine/src/runtime/exitSelector.ts",
      "line": 20,
      "column": 1,
      "code": "ENGINE-STRUCT-003",
      "message": "当前=12  允许=10  函数 selectExit 圈复杂度 12 超过告警线 10  重构条件分支",
      "severity": "warn"
    },
    {
      "file": "packages/rpg-engine/src/runtime/freeCallPostPipeline.ts",
      "line": 37,
      "column": 1,
      "code": "ENGINE-STRUCT-002",
      "message": "当前=88  允许=60  函数 runFreeCallPostPipeline 有效行数 88 超过告警线 60  考虑拆分以保持可测性",
      "severity": "warn"
    },
    {
      "file": "packages/rpg-engine/src/runtime/freeCallPostPipeline.ts",
      "line": 37,
      "column": 1,
      "code": "ENGINE-STRUCT-003",
      "message": "当前=11  允许=10  函数 runFreeCallPostPipeline 圈复杂度 11 超过告警线 10  重构条件分支",
      "severity": "warn"
    },
    {
      "file": "packages/rpg-engine/src/runtime/pickPendingForUserDial.ts",
      "line": 56,
      "column": 1,
      "code": "ENGINE-STRUCT-003",
      "message": "当前=14  允许=10  函数 pickPendingForIntent 圈复杂度 14 超过告警线 10  重构条件分支",
      "severity": "warn"
    },
    {
      "file": "packages/rpg-engine/src/schedule/reconcileRecurringIntents.ts",
      "line": 41,
      "column": 1,
      "code": "ENGINE-STRUCT-003",
      "message": "当前=11  允许=10  函数 reconcileRecurringIntents 圈复杂度 11 超过告警线 10  重构条件分支",
      "severity": "warn"
    },
    {
      "file": "packages/rpg-engine/src/schedule/writeRecurringIntentFromEffect.ts",
      "line": 47,
      "column": 1,
      "code": "ENGINE-STRUCT-003",
      "message": "当前=11  允许=10  函数 writeRecurringIntentFromEffect 圈复杂度 11 超过告警线 10  重构条件分支",
      "severity": "warn"
    },
    {
      "file": "packages/rpg-engine/src/schema/promptScene.ts",
      "line": 63,
      "column": 1,
      "code": "ENGINE-STRUCT-003",
      "message": "当前=15  允许=10  函数 validatePromptScenePatches 圈复杂度 15 超过告警线 10  重构条件分支",
      "severity": "warn"
    },
    {
      "file": "packages/rpg-engine/src/tools/resolveToolPolicy.ts",
      "line": 8,
      "column": 1,
      "code": "ENGINE-STRUCT-003",
      "message": "当前=13  允许=10  函数 resolveToolPolicy 圈复杂度 13 超过告警线 10  重构条件分支",
      "severity": "warn"
    },
    {
      "file": "packages/rpg-engine/tests/host/a-to-b-memory-e2e.test.ts",
      "line": 17,
      "column": 38,
      "code": "ENGINE-STRUCT-002",
      "message": "当前=80  允许=60  函数 <anonymous> 有效行数 80 超过告警线 60  考虑拆分以保持可测性",
      "severity": "warn"
    },
    {
      "file": "packages/rpg-engine/tests/host/a-to-b-memory-e2e.test.ts",
      "line": 27,
      "column": 70,
      "code": "ENGINE-STRUCT-002",
      "message": "当前=71  允许=60  函数 <anonymous> 有效行数 71 超过告警线 60  考虑拆分以保持可测性",
      "severity": "warn"
    },
    {
      "file": "packages/rpg-engine/tests/host/chat-turns-e2e.test.ts",
      "line": 17,
      "column": 37,
      "code": "ENGINE-STRUCT-002",
      "message": "当前=91  允许=60  函数 <anonymous> 有效行数 91 超过告警线 60  考虑拆分以保持可测性",
      "severity": "warn"
    },
    {
      "file": "packages/rpg-engine/tests/host/chat-turns-e2e.test.ts",
      "line": 17,
      "column": 37,
      "code": "ENGINE-STRUCT-003",
      "message": "当前=13  允许=10  函数 <anonymous> 圈复杂度 13 超过告警线 10  重构条件分支",
      "severity": "warn"
    },
    {
      "file": "packages/rpg-engine/tests/host/manual-story-loop.test.ts",
      "line": 21,
      "column": 31,
      "code": "ENGINE-STRUCT-002",
      "message": "当前=86  允许=60  函数 <anonymous> 有效行数 86 超过告警线 60  考虑拆分以保持可测性",
      "severity": "warn"
    },
    {
      "file": "packages/rpg-engine/tests/host/night-layer-e2e.test.ts",
      "line": 17,
      "column": 40,
      "code": "ENGINE-STRUCT-002",
      "message": "当前=75  允许=60  函数 <anonymous> 有效行数 75 超过告警线 60  考虑拆分以保持可测性",
      "severity": "warn"
    },
    {
      "file": "packages/rpg-engine/tests/host/playback-phase.test.ts",
      "line": 20,
      "column": 40,
      "code": "ENGINE-STRUCT-002",
      "message": "当前=94  允许=60  函数 <anonymous> 有效行数 94 超过告警线 60  考虑拆分以保持可测性",
      "severity": "warn"
    },
    {
      "file": "packages/rpg-engine/tests/host/playback-phase.test.ts",
      "line": 30,
      "column": 79,
      "code": "ENGINE-STRUCT-002",
      "message": "当前=85  允许=60  函数 <anonymous> 有效行数 85 超过告警线 60  考虑拆分以保持可测性",
      "severity": "warn"
    },
    {
      "file": "packages/rpg-engine/tests/runtime/composer.localHourRange.test.ts",
      "line": 145,
      "column": 56,
      "code": "ENGINE-STRUCT-002",
      "message": "当前=80  允许=60  函数 <anonymous> 有效行数 80 超过告警线 60  考虑拆分以保持可测性",
      "severity": "warn"
    },
    {
      "file": "packages/rpg-engine/tests/runtime/pick-pending-entry-mode.test.ts",
      "line": 38,
      "column": 41,
      "code": "ENGINE-STRUCT-002",
      "message": "当前=86  允许=60  函数 <anonymous> 有效行数 86 超过告警线 60  考虑拆分以保持可测性",
      "severity": "warn"
    },
    {
      "file": "packages/rpg-engine/tests/schedule/card-reference-and-classify.test.ts",
      "line": 28,
      "column": 43,
      "code": "ENGINE-STRUCT-002",
      "message": "当前=81  允许=60  函数 <anonymous> 有效行数 81 超过告警线 60  考虑拆分以保持可测性",
      "severity": "warn"
    },
    {
      "file": "packages/rpg-engine/tests/schedule/card-reference-and-classify.test.ts",
      "line": 28,
      "column": 43,
      "code": "ENGINE-STRUCT-003",
      "message": "当前=14  允许=10  函数 <anonymous> 圈复杂度 14 超过告警线 10  重构条件分支",
      "severity": "warn"
    },
    {
      "file": "apps/studioV2/app/api/characters/route.ts",
      "line": 54,
      "column": 1,
      "code": "STUDIO-STRUCT-003",
      "message": "函数 POST 圈复杂度 12 超过告警线 10  重构条件分支，避免继续堆叠",
      "severity": "warn"
    },
    {
      "file": "apps/studioV2/app/api/memory/route.ts",
      "line": 10,
      "column": 1,
      "code": "STUDIO-STRUCT-003",
      "message": "函数 GET 圈复杂度 11 超过告警线 10  重构条件分支，避免继续堆叠",
      "severity": "warn"
    },
    {
      "file": "apps/studioV2/src/bis/pageBis/characters/detail/form/characterDefMapper.ts",
      "line": 1,
      "column": 1,
      "code": "STUDIO-STRUCT-001",
      "message": "other 有效行数 377 超过告警线 350  尽快拆分，避免逼近硬上限",
      "severity": "warn"
    },
    {
      "file": "apps/studioV2/src/bis/pageBis/characters/detail/form/characterDefMapper.ts",
      "line": 150,
      "column": 1,
      "code": "STUDIO-STRUCT-002",
      "message": "函数 characterDefToSummary 有效行数 61 超过告警线 60  考虑拆分以保持可测性",
      "severity": "warn"
    },
    {
      "file": "apps/studioV2/src/bis/pageBis/characters/detail/form/characterDefMapper.ts",
      "line": 217,
      "column": 1,
      "code": "STUDIO-STRUCT-002",
      "message": "函数 mergeDetailFormIntoCharacterDef 有效行数 94 超过告警线 60  考虑拆分以保持可测性",
      "severity": "warn"
    }
  ],
  "historyFile": "batch-1-1784288559214.json"
}
